pod5/__init__.py
pod5/_version.py
pod5/api_utils.py
pod5/dataset.py
pod5/pod5_types.py
pod5/reader.py
pod5/repack.py
pod5/signal_tools.py
pod5/writer.py
pod5/tools/__init__.py
pod5/tools/main.py
pod5/tools/parsers.py
pod5/tools/pod5_convert_from_fast5.py
pod5/tools/pod5_convert_to_fast5.py
pod5/tools/pod5_filter.py
pod5/tools/pod5_inspect.py
pod5/tools/pod5_merge.py
pod5/tools/pod5_recover.py
pod5/tools/pod5_repack.py
pod5/tools/pod5_subset.py
pod5/tools/pod5_update.py
pod5/tools/pod5_view.py
pod5/tools/polars_utils.py
pod5/tools/utils.py
pod5-0.3.35.dist-info/METADATA
pod5-0.3.35.dist-info/WHEEL
pod5-0.3.35.dist-info/entry_points.txt
pod5-0.3.35.dist-info/top_level.txt
pod5-0.3.35.dist-info/RECORD
