Metadata-Version: 2.4
Name: pod5
Version: 0.3.35
Summary: Oxford Nanopore Technologies Pod5 File Format Python API and Tools
Author-email: Oxford Nanopore Technologies plc <support@nanoporetech.com>
Project-URL: Homepage, https://github.com/nanoporetech/pod5-file-format
Project-URL: Issues, https://github.com/nanoporetech/pod5-file-format/issues
Project-URL: Documentation, https://pod5-file-format.readthedocs.io/en/latest/
Keywords: nanopore
Classifier: Environment :: Console
Classifier: Intended Audience :: Developers
Classifier: Intended Audience :: Science/Research
Classifier: License :: OSI Approved :: Mozilla Public License 2.0 (MPL 2.0)
Classifier: Natural Language :: English
Classifier: Programming Language :: Python :: 3
Classifier: Topic :: Scientific/Engineering :: Bio-Informatics
Requires-Python: ~=3.9
Requires-Dist: deprecated~=1.2.18
Requires-Dist: lib_pod5==0.3.35
Requires-Dist: iso8601
Requires-Dist: more_itertools
Requires-Dist: numpy>=1.21.0
Requires-Dist: typing-extensions; python_version < "3.10"
Requires-Dist: pyarrow~=22.0.0; python_version >= "3.10"
Requires-Dist: pyarrow~=18.0.0; python_version < "3.10"
Requires-Dist: pytz
Requires-Dist: packaging
Requires-Dist: polars~=1.30
Requires-Dist: h5py~=3.11
Requires-Dist: vbz_h5py_plugin
Requires-Dist: tqdm
Provides-Extra: dev
Requires-Dist: black==23.3.0; extra == "dev"
Requires-Dist: mypy==1.3.0; extra == "dev"
Requires-Dist: pre-commit==v2.21.0; extra == "dev"
Requires-Dist: psutil; extra == "dev"
Requires-Dist: pytest~=7.3; extra == "dev"
Requires-Dist: pytest-cov~=4.0; extra == "dev"
Requires-Dist: pytest-mock; extra == "dev"
Requires-Dist: types-Deprecated; extra == "dev"
Requires-Dist: types-setuptools; extra == "dev"
Requires-Dist: types-pytz; extra == "dev"
